setup.py
cosmic_distributions/Binomialdistribution.py
cosmic_distributions/Gaussiandistribution.py
cosmic_distributions/Generaldistribution.py
cosmic_distributions/__init__.py
cosmic_distributions.egg-info/PKG-INFO
cosmic_distributions.egg-info/SOURCES.txt
cosmic_distributions.egg-info/dependency_links.txt
cosmic_distributions.egg-info/not-zip-safe
cosmic_distributions.egg-info/top_level.txt