Metadata-Version: 1.0
Name: cosmic-distributions
Version: 0.1
Summary: Gaussian and Binomial distributions
Home-page: UNKNOWN
Author: Markus Huber
Author-email: mbhuber@yahoo.com
License: UNKNOWN
Platform: UNKNOWN
